protools/__init__.py
protools/__main__.py
protools/cli.py
protools/bin/protoc-3.18.0-linux-aarch_64
protools/bin/protoc-3.18.0-linux-ppcle_64
protools/bin/protoc-3.18.0-linux-s390_64
protools/bin/protoc-3.18.0-linux-x86_32
protools/bin/protoc-3.18.0-linux-x86_64
protools/bin/protoc-3.18.0-osx-x86_64
protools/bin/protoc-3.18.0-win32.exe
protools/bin/protoc-3.18.0-win64.exe
protools-1.0.2.dist-info/LICENSE
protools-1.0.2.dist-info/METADATA
protools-1.0.2.dist-info/WHEEL
protools-1.0.2.dist-info/entry_points.txt
protools-1.0.2.dist-info/top_level.txt
protools-1.0.2.dist-info/RECORD
