Metadata-Version: 2.1
Name: protools
Version: 1.0.2
Summary: 一个实现了批量将 protobuf 数据自动识别为类 json 格式，批量将 proto 定义文件转为 python 类的命令行工具。适用于需要转换大量的 protobuf 数据或 proto 定义文件。
Home-page: https://github.com/WankkoRee/protools
Author: Wankko Ree
Author-email: wkr@wkr.moe
License: GPLv3
Project-URL: Bug Tracker, https://github.com/WankkoRee/protools/issues
Platform: UNKNOWN
Classifier: Development Status :: 4 - Beta
Classifier: Programming Language :: Python :: 3 :: Only
Classifier: Programming Language :: Python :: 3.7
Classifier: Programming Language :: Python :: 3.8
Classifier: Programming Language :: Python :: 3.9
Classifier: License :: OSI Approved :: GNU General Public License v3 (GPLv3)
Classifier: Operating System :: OS Independent
Classifier: Natural Language :: Chinese (Simplified)
Requires-Python: >=3.7
License-File: LICENSE
Requires-Dist: rich (~=10.10.0)
Requires-Dist: rich-LogConsole (~=1.0.2)
